{"namedChunkGroups":{"polyfill":{"name":"polyfill","assets":[{"name":"webpack-runtime-f4976c55bd465a45abbe.js","size":1584},{"name":"polyfill-f0f176fae4d544d25342.js","size":82624}],"filteredAssets":0,"assetsSize":84208,"filteredAuxiliaryAssets":2,"auxiliaryAssetsSize":207150},"app":{"name":"app","assets":[{"name":"webpack-runtime-f4976c55bd465a45abbe.js","size":1584},{"name":"framework-3f0c9db065708f9044b5.js","size":11478},{"name":"styles.fd955da0eaebc54e9685.css","size":206695},{"name":"a284c5a4-9f470720b6ed353b377f.js","size":118413},{"name":"app-828fce21753e479bfdc4.js","size":2848103}],"filteredAssets":0,"assetsSize":3186273,"filteredAuxiliaryAssets":4,"auxiliaryAssetsSize":5574156}},"assetsByChunkName":{"polyfill":["webpack-runtime-f4976c55bd465a45abbe.js","polyfill-f0f176fae4d544d25342.js"],"app":["webpack-runtime-f4976c55bd465a45abbe.js","framework-3f0c9db065708f9044b5.js","styles.fd955da0eaebc54e9685.css","a284c5a4-9f470720b6ed353b377f.js","app-828fce21753e479bfdc4.js"]},"childAssetsByChunkName":{}}